{
    "template": {
        "_id": 205,
        "合金成分及热处理制度": {
            "_type": "表格型",
            "合金名称（at %）": {
                "_type": "字符串型"
            },
            "固溶温度1-1（℃）": {
                "_type": "字符串型"
            },
            "固溶时间1-1（h）": {
                "_type": "字符串型"
            },
            "固溶温度1-2（℃）": {
                "_type": "字符串型"
            },
            "固溶时间1-2（h）": {
                "_type": "字符串型"
            },
            "时效温度（℃）": {
                "_type": "字符串型"
            },
            "时效时间（h）": {
                "_type": "字符串型"
            }
        },
        "性能1": {
            "_type": "表格型",
            "γ'相溶解温度（℃）": {
                "_type": "字符串型"
            },
            "固相线温度（℃）": {
                "_type": "字符串型"
            },
            "液相线温度（℃）": {
                "_type": "字符串型"
            },
            "密度（g/cm3）": {
                "_type": "字符串型"
            },
            "γ'相体积分数（%）": {
                "_type": "字符串型"
            },
            "Vickers microhardness（Gpa）": {
                "_type": "字符串型"
            },
            "洛氏硬度（HRC）": {
                "_type": "字符串型"
            },
            "维氏硬度（Hv）": {
                "_type": "字符串型"
            }
        },
        "性能2": {
            "_type": "表格型",
            "γ'相尺寸（nm）": {
                "_type": "字符串型"
            },
            "Lattice misfit（%）": {
                "_type": "字符串型"
            },
            "Tensile test": {
                "_type": "字符串型"
            },
            "Elongation at break（%）": {
                "_type": "字符串型"
            },
            "γ'area fractions Af（%）": {
                "_type": "字符串型"
            },
            "Mean oxide layer thickness": {
                "_type": "字符串型"
            }
        }
    },
    "data": [
        {
            "meta": {
                "数据 ID": "***第1个数据的ID***",
                "标题": "在这里填写 标题",
                "DOI": "在这里填写 DOI",
                "数据摘要": "在这里填写 数据摘要",
                "关键词": "在这里填写 关键词",
                "来源": "MGE-SOURCE_HEADER v1 000 10 #",
                "引用": "在这里填写 引用",
                "其他信息": "project: 2016YFB0700500；subject: 2016YFB0700503"
            },
            "content": {
                "合金成分及热处理制度": [
                    {
                        "合金名称（at %）": "在这里填写 合金名称（at %） (字符串型)",
                        "固溶温度1-1（℃）": "在这里填写 固溶温度1-1（℃） (字符串型)",
                        "固溶时间1-1（h）": "在这里填写 固溶时间1-1（h） (字符串型)",
                        "固溶温度1-2（℃）": "在这里填写 固溶温度1-2（℃） (字符串型)",
                        "固溶时间1-2（h）": "在这里填写 固溶时间1-2（h） (字符串型)",
                        "时效温度（℃）": "在这里填写 时效温度（℃） (字符串型)",
                        "时效时间（h）": "在这里填写 时效时间（h） (字符串型)"
                    },
                    {
                        "合金名称（at %）": "在这里填写 合金名称（at %） (字符串型)",
                        "固溶温度1-1（℃）": "在这里填写 固溶温度1-1（℃） (字符串型)",
                        "固溶时间1-1（h）": "在这里填写 固溶时间1-1（h） (字符串型)",
                        "固溶温度1-2（℃）": "在这里填写 固溶温度1-2（℃） (字符串型)",
                        "固溶时间1-2（h）": "在这里填写 固溶时间1-2（h） (字符串型)",
                        "时效温度（℃）": "在这里填写 时效温度（℃） (字符串型)",
                        "时效时间（h）": "在这里填写 时效时间（h） (字符串型)"
                    }
                ],
                "性能1": [
                    {
                        "γ'相溶解温度（℃）": "在这里填写 γ'相溶解温度（℃） (字符串型)",
                        "固相线温度（℃）": "在这里填写 固相线温度（℃） (字符串型)",
                        "液相线温度（℃）": "在这里填写 液相线温度（℃） (字符串型)",
                        "密度（g/cm3）": "在这里填写 密度（g/cm3） (字符串型)",
                        "γ'相体积分数（%）": "在这里填写 γ'相体积分数（%） (字符串型)",
                        "Vickers microhardness（Gpa）": "在这里填写 Vickers microhardness（Gpa） (字符串型)",
                        "洛氏硬度（HRC）": "在这里填写 洛氏硬度（HRC） (字符串型)",
                        "维氏硬度（Hv）": "在这里填写 维氏硬度（Hv） (字符串型)"
                    },
                    {
                        "γ'相溶解温度（℃）": "在这里填写 γ'相溶解温度（℃） (字符串型)",
                        "固相线温度（℃）": "在这里填写 固相线温度（℃） (字符串型)",
                        "液相线温度（℃）": "在这里填写 液相线温度（℃） (字符串型)",
                        "密度（g/cm3）": "在这里填写 密度（g/cm3） (字符串型)",
                        "γ'相体积分数（%）": "在这里填写 γ'相体积分数（%） (字符串型)",
                        "Vickers microhardness（Gpa）": "在这里填写 Vickers microhardness（Gpa） (字符串型)",
                        "洛氏硬度（HRC）": "在这里填写 洛氏硬度（HRC） (字符串型)",
                        "维氏硬度（Hv）": "在这里填写 维氏硬度（Hv） (字符串型)"
                    }
                ],
                "性能2": [
                    {
                        "γ'相尺寸（nm）": "在这里填写 γ'相尺寸（nm） (字符串型)",
                        "Lattice misfit（%）": "在这里填写 Lattice misfit（%） (字符串型)",
                        "Tensile test": "在这里填写 Tensile test (字符串型)",
                        "Elongation at break（%）": "在这里填写 Elongation at break（%） (字符串型)",
                        "γ'area fractions Af（%）": "在这里填写 γ'area fractions Af（%） (字符串型)",
                        "Mean oxide layer thickness": "在这里填写 Mean oxide layer thickness (字符串型)"
                    },
                    {
                        "γ'相尺寸（nm）": "在这里填写 γ'相尺寸（nm） (字符串型)",
                        "Lattice misfit（%）": "在这里填写 Lattice misfit（%） (字符串型)",
                        "Tensile test": "在这里填写 Tensile test (字符串型)",
                        "Elongation at break（%）": "在这里填写 Elongation at break（%） (字符串型)",
                        "γ'area fractions Af（%）": "在这里填写 γ'area fractions Af（%） (字符串型)",
                        "Mean oxide layer thickness": "在这里填写 Mean oxide layer thickness (字符串型)"
                    }
                ]
            }
        },
        {
            "meta": {
                "数据 ID": "***第2个数据的ID***",
                "标题": "在这里填写 标题",
                "DOI": "在这里填写 DOI",
                "数据摘要": "在这里填写 数据摘要",
                "关键词": "在这里填写 关键词",
                "来源": "MGE-SOURCE_HEADER v1 000 10 #",
                "引用": "在这里填写 引用",
                "其他信息": "project: 2016YFB0700500；subject: 2016YFB0700503"
            },
            "content": {
                "合金成分及热处理制度": [
                    {
                        "合金名称（at %）": "在这里填写 合金名称（at %） (字符串型)",
                        "固溶温度1-1（℃）": "在这里填写 固溶温度1-1（℃） (字符串型)",
                        "固溶时间1-1（h）": "在这里填写 固溶时间1-1（h） (字符串型)",
                        "固溶温度1-2（℃）": "在这里填写 固溶温度1-2（℃） (字符串型)",
                        "固溶时间1-2（h）": "在这里填写 固溶时间1-2（h） (字符串型)",
                        "时效温度（℃）": "在这里填写 时效温度（℃） (字符串型)",
                        "时效时间（h）": "在这里填写 时效时间（h） (字符串型)"
                    },
                    {
                        "合金名称（at %）": "在这里填写 合金名称（at %） (字符串型)",
                        "固溶温度1-1（℃）": "在这里填写 固溶温度1-1（℃） (字符串型)",
                        "固溶时间1-1（h）": "在这里填写 固溶时间1-1（h） (字符串型)",
                        "固溶温度1-2（℃）": "在这里填写 固溶温度1-2（℃） (字符串型)",
                        "固溶时间1-2（h）": "在这里填写 固溶时间1-2（h） (字符串型)",
                        "时效温度（℃）": "在这里填写 时效温度（℃） (字符串型)",
                        "时效时间（h）": "在这里填写 时效时间（h） (字符串型)"
                    }
                ],
                "性能1": [
                    {
                        "γ'相溶解温度（℃）": "在这里填写 γ'相溶解温度（℃） (字符串型)",
                        "固相线温度（℃）": "在这里填写 固相线温度（℃） (字符串型)",
                        "液相线温度（℃）": "在这里填写 液相线温度（℃） (字符串型)",
                        "密度（g/cm3）": "在这里填写 密度（g/cm3） (字符串型)",
                        "γ'相体积分数（%）": "在这里填写 γ'相体积分数（%） (字符串型)",
                        "Vickers microhardness（Gpa）": "在这里填写 Vickers microhardness（Gpa） (字符串型)",
                        "洛氏硬度（HRC）": "在这里填写 洛氏硬度（HRC） (字符串型)",
                        "维氏硬度（Hv）": "在这里填写 维氏硬度（Hv） (字符串型)"
                    },
                    {
                        "γ'相溶解温度（℃）": "在这里填写 γ'相溶解温度（℃） (字符串型)",
                        "固相线温度（℃）": "在这里填写 固相线温度（℃） (字符串型)",
                        "液相线温度（℃）": "在这里填写 液相线温度（℃） (字符串型)",
                        "密度（g/cm3）": "在这里填写 密度（g/cm3） (字符串型)",
                        "γ'相体积分数（%）": "在这里填写 γ'相体积分数（%） (字符串型)",
                        "Vickers microhardness（Gpa）": "在这里填写 Vickers microhardness（Gpa） (字符串型)",
                        "洛氏硬度（HRC）": "在这里填写 洛氏硬度（HRC） (字符串型)",
                        "维氏硬度（Hv）": "在这里填写 维氏硬度（Hv） (字符串型)"
                    }
                ],
                "性能2": [
                    {
                        "γ'相尺寸（nm）": "在这里填写 γ'相尺寸（nm） (字符串型)",
                        "Lattice misfit（%）": "在这里填写 Lattice misfit（%） (字符串型)",
                        "Tensile test": "在这里填写 Tensile test (字符串型)",
                        "Elongation at break（%）": "在这里填写 Elongation at break（%） (字符串型)",
                        "γ'area fractions Af（%）": "在这里填写 γ'area fractions Af（%） (字符串型)",
                        "Mean oxide layer thickness": "在这里填写 Mean oxide layer thickness (字符串型)"
                    },
                    {
                        "γ'相尺寸（nm）": "在这里填写 γ'相尺寸（nm） (字符串型)",
                        "Lattice misfit（%）": "在这里填写 Lattice misfit（%） (字符串型)",
                        "Tensile test": "在这里填写 Tensile test (字符串型)",
                        "Elongation at break（%）": "在这里填写 Elongation at break（%） (字符串型)",
                        "γ'area fractions Af（%）": "在这里填写 γ'area fractions Af（%） (字符串型)",
                        "Mean oxide layer thickness": "在这里填写 Mean oxide layer thickness (字符串型)"
                    }
                ]
            }
        }
    ]
}